datalake/__init__.py
datalake/logging_helpers.py
datalake/archive.py
datalake/queue.py
datalake/config_helpers.py
datalake/translator.py
datalake/crtime.py
datalake/_version.py
datalake/dlfile.py
datalake/scripts/__init__.py
datalake/scripts/cli.py
datalake_dtkav-0.36.dist-info/RECORD
datalake_dtkav-0.36.dist-info/WHEEL
datalake_dtkav-0.36.dist-info/DESCRIPTION.rst
datalake_dtkav-0.36.dist-info/metadata.json
datalake_dtkav-0.36.dist-info/entry_points.txt
datalake_dtkav-0.36.dist-info/METADATA
datalake_dtkav-0.36.dist-info/top_level.txt
