Metadata-Version: 2.0
Name: datalake-dtkav
Version: 0.36
Summary: datalake-dtkav: a fork of planetlabs/datalake
Home-page: https://github.com/dtkav/datalake
Author: Daniel Grossmann-Kavanagh, Brian Cavagnolo
Author-email: me@danielgk.com
License: UNKNOWN
Platform: UNKNOWN
Classifier: Programming Language :: Python :: 2.7
Classifier: Programming Language :: Python :: 3.5
Provides-Extra: krb
Provides-Extra: sentry
Provides-Extra: queuable
Provides-Extra: test
Requires-Dist: boto (>=2.38.0)
Requires-Dist: memoized-property (>=1.0.1)
Requires-Dist: simplejson (>=3.3.1)
Requires-Dist: pyblake2 (>=0.9.3)
Requires-Dist: click (>=4.1)
Requires-Dist: datalake-common-dtkav (>=0.29)
Requires-Dist: python-dotenv (>=0.1.3)
Requires-Dist: requests (>=2.5)
Requires-Dist: six (>=1.10.0)
Requires-Dist: py-multibase (>=1.0.1)
Requires-Dist: py-multihash (>=0.2.3)
Provides-Extra: krb
Requires-Dist: requests-kerberos (>=0.10.0); extra == 'krb'
Provides-Extra: queuable
Requires-Dist: pyinotify (>=0.9.4); extra == 'queuable'
Provides-Extra: sentry
Requires-Dist: raven (>=5.0.0); extra == 'sentry'
Provides-Extra: test
Requires-Dist: pytest (==3.0.2); extra == 'test'
Requires-Dist: moto (==0.4.27); extra == 'test'
Requires-Dist: twine (==1.5.0); extra == 'test'
Requires-Dist: pip (==7.1.0); extra == 'test'
Requires-Dist: wheel (==0.24.0); extra == 'test'
Requires-Dist: flake8 (==2.5.0); extra == 'test'
Requires-Dist: responses (==0.5.0); extra == 'test'
Requires-Dist: pytz (>=2015.4); extra == 'test'
